schema_evolution.py
schema_evolution-1.0.0.dist-info/METADATA
schema_evolution-1.0.0.dist-info/WHEEL
schema_evolution-1.0.0.dist-info/RECORD
