Metadata-Version: 2.3
Name: schema-evolution
Version: 1.0.0
Summary: A reusable package for handling schema evolution in Spark/Hive tables
Home-page: https://github.com/ksmc/schema-evolution
License: MIT
Keywords: spark,hive,schema,evolution,data,engineering
Author: KSMC Data Engineering
Author-email: data-engineering@ksmc.gov.sa
Requires-Python: >=3.6,<4.0
Classifier: Development Status :: 4 - Beta
Classifier: Intended Audience :: Developers
Classifier: License :: OSI Approved :: MIT License
Classifier: Programming Language :: Python :: 3
Classifier: Programming Language :: Python :: 3.6
Classifier: Programming Language :: Python :: 3.7
Classifier: Programming Language :: Python :: 3.8
Classifier: Programming Language :: Python :: 3.9
Classifier: Programming Language :: Python :: 3.10
Classifier: Programming Language :: Python :: 3.11
Classifier: Programming Language :: Python :: 3.12
Classifier: Programming Language :: Python :: 3.13
Classifier: Topic :: Software Development :: Libraries :: Python Modules
Requires-Dist: pyspark (>=3.0.0,<4.0.0)
Project-URL: Repository, https://github.com/ksmc/schema-evolution
